<?xml version="1.0" encoding="UTF-8" ?>
<plugin_manifest xmlns="http://www.elgg.org/plugin_manifest/1.8">
	<name>Google Calendar</name>
	<author>THINK Global School</author>
	<version>1.8</version>
	<category>enhancement</category>
	<category>tgs</category>
	<description>Provides Google Calendar integration</description>
	<website>http://thinkglobalschool.org</website>
	<copyright>THINK Global School 2010 - 2014</copyright>
	<licence>GNU Public License version 2</licence>
	<activate_on_install>true</activate_on_install>
   	<requires>
		<type>elgg_release</type>
		<version>1.8</version>
	</requires>
</plugin_manifest>
